cartouche_ocr/__init__.py
cartouche_ocr/cartouche_detect.py
cartouche_ocr/ocr.py
cartouche_ocr-0.0.1.dist-info/LICENSE
cartouche_ocr-0.0.1.dist-info/METADATA
cartouche_ocr-0.0.1.dist-info/WHEEL
cartouche_ocr-0.0.1.dist-info/top_level.txt
cartouche_ocr-0.0.1.dist-info/RECORD
