Metadata-Version: 2.1
Name: cartouche-ocr
Version: 0.0.1
Summary: package to detect and ocr cartouche
Author-email: Ahsan IQBAL <ahsan.iqbal@setec.com>
License: Copyright (c) 2018 The Python Packaging Authority        
Classifier: Programming Language :: Python :: 3
Classifier: License :: OSI Approved :: MIT License
Classifier: Operating System :: OS Independent
Requires-Python: >=3.7
License-File: LICENSE
